LICENSE
MANIFEST.in
README.rst
pytest_count.py
setup.cfg
setup.py
pytest_count.egg-info/PKG-INFO
pytest_count.egg-info/SOURCES.txt
pytest_count.egg-info/dependency_links.txt
pytest_count.egg-info/entry_points.txt
pytest_count.egg-info/requires.txt
pytest_count.egg-info/top_level.txt